fmipp/__init__.py
fmipp/extractFMU.py
fmipp/fmippim.py
fmipp/numeric.py
fmipp/pathToURI.py
fmipp/simplifyModelDescription.py
fmipp/export/FMIAdapterBase.py
fmipp/export/FMIAdapterV2.py
fmipp/export/__init__.py
fmipp/export/createFMU.py
fmipp/export/fmi1.py
fmipp/export/fmi2.py
fmipp/export/fmippex.py
fmipp/export/runFMUBackend.py
fmipp/export/bin/README.md
fmipp/export/bin/fmi2.dll
fmipp/export/bin/libfmipp_fmu_frontend.lib
fmipp/lib/README.md
fmipp/lib/_fmippex.pyd
fmipp/lib/_fmippim.pyd
fmipp/lib/fmippex.dll
fmipp/lib/fmippim.dll
fmipp/lib/msvcp140.dll
fmipp/lib/sundials_cvode.dll
fmipp/lib/vcruntime140.dll
fmipp/lib/vcruntime140_1.dll
fmipp-2.1.0.dist-info/METADATA
fmipp-2.1.0.dist-info/WHEEL
fmipp-2.1.0.dist-info/top_level.txt
fmipp-2.1.0.dist-info/RECORD
