Metadata-Version: 2.1
Name: fmipp
Version: 2.1.0
Summary: FMI++ Python Interface
Home-page: https://fmipp.readthedocs.io/projects/py-fmipp
Maintainer: Edmund Widl
Maintainer-email: edmund.widl@ait.ac.at
License: BSD license & BOOST software license
Keywords: FMI,Functional Mock-up Interface,FMI++ Library
Platform: Windows
Classifier: Development Status :: 5 - Production/Stable
Classifier: Intended Audience :: Science/Research
Classifier: Operating System :: Microsoft :: Windows
Classifier: Operating System :: POSIX :: Linux
Classifier: Topic :: Scientific/Engineering
Classifier: Programming Language :: Python :: 2.7
Classifier: Programming Language :: Python :: 3.10
Classifier: Programming Language :: C++
